proxycraft/__init__.py
proxycraft/default.json
proxycraft/logger.py
proxycraft/proxycraft.py
proxycraft/py.typed
proxycraft/config/__init__.py
proxycraft/config/loader.py
proxycraft/config/models.py
proxycraft/files/__init__.py
proxycraft/files/reader/__init__.py
proxycraft/files/reader/io_async_reader.py
proxycraft/middlewares/__init__.py
proxycraft/middlewares/content_length_middleware.py
proxycraft/middlewares/performance/__init__.py
proxycraft/middlewares/performance/circuit_breaker.py
proxycraft/middlewares/performance/compression.py
proxycraft/middlewares/performance/resource_filter.py
proxycraft/middlewares/performance/caching/__init__.py
proxycraft/middlewares/performance/caching/in_file.py
proxycraft/middlewares/performance/caching/in_memory.py
proxycraft/middlewares/security/__init__.py
proxycraft/middlewares/security/bot_filter.py
proxycraft/middlewares/security/ip_filter.py
proxycraft/middlewares/transformer/__init__.py
proxycraft/middlewares/transformer/request_transform.py
proxycraft/middlewares/transformer/response_transform.py
proxycraft/networking/__init__.py
proxycraft/networking/connection_pooling/__init__.py
proxycraft/networking/connection_pooling/connection_pooling.py
proxycraft/networking/connection_pooling/http_client.py
proxycraft/networking/connection_pooling/http_constants.py
proxycraft/networking/connection_pooling/connectors/__init__.py
proxycraft/networking/connection_pooling/connectors/connector_sage_singleton.py
proxycraft/networking/connection_pooling/connectors/context_connector.py
proxycraft/networking/connection_pooling/connectors/event_loop_connector_manager.py
proxycraft/networking/connection_pooling/connectors/thread_local_connector.py
proxycraft/networking/connection_pooling/tracing/__init__.py
proxycraft/networking/connection_pooling/tracing/default_trace_handler.py
proxycraft/networking/load_balancing/__init__.py
proxycraft/networking/routing/__init__.py
proxycraft/networking/routing/routing_selector.py
proxycraft-1.0.3.dist-info/METADATA
proxycraft-1.0.3.dist-info/WHEEL
proxycraft-1.0.3.dist-info/entry_points.txt
proxycraft-1.0.3.dist-info/licenses/LICENSE
proxycraft-1.0.3.dist-info/RECORD
