Metadata-Version: 2.4
Name: proxycraft
Version: 1.0.3
Summary: ⚡ High-performance Python proxy server with authentication, load balancing, caching, and multi-protocol support
Project-URL: homepage, https://github.com/sylvainmouquet/proxycraft
Project-URL: documentation, https://github.com/sylvainmouquet/proxycraft
Project-URL: repository, https://github.com/sylvainmouquet/proxycraft
Project-URL: changelog, https://github.com/sylvainmouquet/proxycraft/releases
Author-email: Sylvain Mouquet <sylvain.mouquet@gmail.com>
License: MIT
License-File: LICENSE
Keywords: authentication,http,https,load-balancing,networking,proxy,proxycraft,python,reverse-proxy,socks5,websocket
Classifier: Development Status :: 5 - Production/Stable
Classifier: Framework :: Pytest
Classifier: Intended Audience :: Developers
Classifier: License :: OSI Approved :: MIT License
Classifier: Programming Language :: Python
Classifier: Programming Language :: Python :: 3
Classifier: Programming Language :: Python :: 3.13
Classifier: Topic :: Software Development :: Libraries :: Python Modules
Requires-Python: >=3.13
Requires-Dist: aiofile>=3.9.0
Requires-Dist: aiofiles>=24.1.0
Requires-Dist: aiohttp>=3.11.18
Requires-Dist: antpathmatcher>=1.0.0
Requires-Dist: apscheduler>=3.11.0
Requires-Dist: curl-cffi>=0.11.2
Requires-Dist: granian>=2.3.3
Requires-Dist: gunicorn>=23.0.0
Requires-Dist: httpx>=0.28.1
Requires-Dist: hypercorn>=0.17.3
Requires-Dist: pydantic>=2.11.4
Requires-Dist: python-jose>=3.4.0
Requires-Dist: robyn>=0.68.0
Requires-Dist: starlette>=0.50
Requires-Dist: structlog>=25.3.0
Requires-Dist: uvicorn-worker>=0.4.0
Requires-Dist: uvicorn>=0.40
Requires-Dist: uvloop>=0.21.0
